{
	"credit": "Made with Blockbench",
	"textures": {
		"1": "adchimneys:blocks/chimney_iron",
		"2": "adchimneys:blocks/chimney_iron_inside",
		"3": "adchimneys:blocks/chimney_iron_top",
		"particle": "adchimneys:blocks/chimney_iron"
	},
	"elements": [
		{
			"from": [13.71536, 0, 13.71536],
			"to": [16.0015, 16, 16.0015],
			"rotation": {"angle": 0, "axis": "y", "origin": [8, 8, 8]},
			"faces": {
				"east": {"uv": [1, 0, 3, 16], "texture": "#1", "cullface": "east"},
				"south": {"uv": [13, 0, 15, 16], "texture": "#1", "cullface": "south"},
				"up": {"uv": [13, 13, 15, 15], "texture": "#3", "cullface": "up"},
				"down": {"uv": [13, 1, 15, 3], "texture": "#3", "cullface": "down"}
			}
		},
		{
			"from": [-0.0015, 0, 13.71536],
			"to": [2.28464, 16, 16.0015],
			"rotation": {"angle": 0, "axis": "y", "origin": [8, 8, 8]},
			"faces": {
				"south": {"uv": [1, 0, 3, 16], "texture": "#1", "cullface": "south"},
				"west": {"uv": [13, 0, 15, 16], "texture": "#1"},
				"up": {"uv": [1, 13, 3, 15], "texture": "#3", "cullface": "up"},
				"down": {"uv": [1, 1, 3, 3], "texture": "#3", "cullface": "down"}
			}
		},
		{
			"from": [-0.0015, 0, -0.0015],
			"to": [2.28464, 16, 2.28464],
			"rotation": {"angle": 0, "axis": "y", "origin": [8, 8, 8]},
			"faces": {
				"north": {"uv": [13, 0, 15, 16], "texture": "#1"},
				"west": {"uv": [1, 0, 3, 16], "texture": "#1"},
				"up": {"uv": [1, 1, 3, 3], "texture": "#3", "cullface": "up"},
				"down": {"uv": [1, 13, 3, 15], "texture": "#3", "cullface": "down"}
			}
		},
		{
			"from": [13.71536, 0, -0.0015],
			"to": [16.0015, 16, 2.28464],
			"rotation": {"angle": 0, "axis": "y", "origin": [8, 8, 8]},
			"faces": {
				"north": {"uv": [1, 0, 3, 16], "texture": "#1"},
				"east": {"uv": [13, 0, 15, 16], "texture": "#1", "cullface": "east"},
				"up": {"uv": [13, 1, 15, 3], "texture": "#3", "cullface": "up"},
				"down": {"uv": [13, 13, 15, 15], "texture": "#3", "cullface": "down"}
			}
		},
		{
			"from": [-0.0015, 0, 2.28464],
			"to": [2.28464, 16, 13.71536],
			"rotation": {"angle": 0, "axis": "y", "origin": [8, 8, 8]},
			"faces": {
				"east": {"uv": [3, 0, 13, 16], "texture": "#2"},
				"west": {"uv": [3, 0, 13, 16], "texture": "#1", "cullface": "west"},
				"up": {"uv": [1, 3, 3, 13], "texture": "#3", "cullface": "up"},
				"down": {"uv": [1, 3, 3, 13], "texture": "#3", "cullface": "down"}
			}
		},
		{
			"from": [13.71536, 0, 2.28464],
			"to": [16.0015, 16, 13.71536],
			"rotation": {"angle": 0, "axis": "y", "origin": [8, 8, 8]},
			"faces": {
				"east": {"uv": [3, 0, 13, 16], "texture": "#1", "cullface": "east"},
				"west": {"uv": [3, 0, 13, 16], "texture": "#2"},
				"up": {"uv": [13, 3, 15, 13], "texture": "#3", "cullface": "up"},
				"down": {"uv": [13, 3, 15, 13], "texture": "#3", "cullface": "down"}
			}
		},
		{
			"from": [2.28464, 0, 13.71536],
			"to": [13.71536, 16, 16.0015],
			"rotation": {"angle": 0, "axis": "y", "origin": [8, 8, 8]},
			"faces": {
				"north": {"uv": [3, 0, 13, 16], "texture": "#2"},
				"south": {"uv": [3, 0, 13, 16], "texture": "#1", "cullface": "south"},
				"up": {"uv": [3, 13, 13, 15], "texture": "#3", "cullface": "up"},
				"down": {"uv": [3, 1, 13, 3], "texture": "#3", "cullface": "down"}
			}
		},
		{
			"from": [2.28464, 0, -0.0015],
			"to": [13.71536, 16, 2.28464],
			"rotation": {"angle": 0, "axis": "y", "origin": [8, 8, 8]},
			"faces": {
				"north": {"uv": [3, 0, 13, 16], "texture": "#1", "cullface": "north"},
				"south": {"uv": [3, 0, 13, 16], "texture": "#2"},
				"up": {"uv": [3, 1, 13, 3], "texture": "#3", "cullface": "up"},
				"down": {"uv": [3, 13, 13, 15], "texture": "#3", "cullface": "down"}
			}
		}
	],
	"groups": [
		{
			"name": "edges",
			"origin": [8, 8, 8],
			"color": 0,
			"children": [0, 1, 2, 3]
		},
		{
			"name": "sides",
			"origin": [8, 8, 8],
			"color": 0,
			"children": [4, 5, 6, 7]
		}
	]
}